setup.py
twiddle
twiddle/__init__.py
twiddle/twiddle
twiddle.egg-info/PKG-INFO
twiddle.egg-info/SOURCES.txt
twiddle.egg-info/dependency_links.txt
twiddle.egg-info/requires.txt
twiddle.egg-info/top_level.txt