Metadata-Version: 1.0
Name: twiddle
Version: 0.0.4
Summary: archive all the twiddles
Home-page: http://github.com/oyouareatubeo/twiddle
Author: Jake Johnson
Author-email: oyouareatubeo@gmail.com
License: UNKNOWN
Platform: UNKNOWN
